setup.py
atams/ChannelParams.py
atams/SetupRsync.py
atams/__init__.py
atams/__init__.pyc
atams/atams.py
atams/atams.pyc
atams/atams.wsgi
atams/atm1.db
atams/channelsvalidity.py
atams/channelsvalidity.pyc
atams/ephemerisvalidity.py
atams/ephemerisvalidity.pyc
atams/libo3bsdbsdk.so
atams/main.py
atams/schedulevalidity.py
atams/schedulevalidity.pyc
atams/schevents.py
atams/schevents.pyc
atams/sqliteConn.py
atams/sqliteConn.pyc
atams/structures.py
atams/structures.pyc
atams/test.py
atams/test1.py
atams_test_version.egg-info/PKG-INFO
atams_test_version.egg-info/SOURCES.txt
atams_test_version.egg-info/dependency_links.txt
atams_test_version.egg-info/not-zip-safe
atams_test_version.egg-info/top_level.txt