Metadata-Version: 1.0
Name: atams-test-version
Version: 0.16
Summary: 1st prog
Home-page: UNKNOWN
Author: UNKNOWN
Author-email: UNKNOWN
License: UNKNOWN
Platform: UNKNOWN
